pycrdt_xml-0.10.5.dist-info/METADATA
pycrdt_xml-0.10.5.dist-info/WHEEL
pycrdt_xml-0.10.5.dist-info/licenses/LICENSE
pycrdt/_awareness.py
pycrdt/_xml.py
pycrdt/_transaction.py
pycrdt/_map.py
pycrdt/_text.py
pycrdt/_doc.py
pycrdt/__init__.py
pycrdt/_base.py
pycrdt/_update.py
pycrdt/_undo.py
pycrdt/_pycrdt.pyi
pycrdt/_array.py
pycrdt/_sync.py
pycrdt/py.typed
pycrdt/_pycrdt.cpython-312-s390x-linux-gnu.so
pycrdt_xml-0.10.5.dist-info/RECORD
